{
  "getlunbo": [
    {
      "id": 1,
      "img": "https://m.360buyimg.com/mobilecms/s700x280_jfs/t1/64512/17/14296/88305/5dbbf1d2Ec5281fb6/bb2dbc7e17920b54.jpg!cr_1125x445_0_171!q70.jpg.dpg",
      "describe": ""
    },
    {
      "id": 2,
      "img": "https://m.360buyimg.com/mobilecms/s700x280_jfs/t1/77793/23/6816/156942/5d50b517Ecaf87409/76563c4d59d55b21.jpg!cr_1125x445_0_171!q70.jpg.dpg",
      "describe": ""
    },
    {
      "id": 3,
      "img": "https://m.360buyimg.com/mobilecms/s700x280_jfs/t1/91690/15/12953/83919/5e537c91Eda127bbf/6249be8cf048a2fa.jpg!cr_1125x445_0_171!q70.jpg.dpg",
      "describe": ""
    }
  ],
  "news": [
    {
      "nid": 1,
      "titele": "科颜氏白泥使用测评",
      "add_time": "2020-03-03",
      "zhaiyao": "\uD83D\uDD3A昨日日上回来带了一大堆东西，买了好友推荐的白泥（主要是在茵芙莎柜台做了肌肤测试，结果说我的角质有点厚，缺水，我一直以为自己角质层很薄，易过敏，就买了这款白泥清洁面膜）",
      "click": 1,
      "img_url": "http://img1.lukou.com/static/p/blog/medium/0023/96/88/99/23968899.jpg",
      "content": "<div class=\"blog-content\">    \uD83D\uDD3A昨日日上回来带了一大堆东西，买了好友推荐的白泥<img src=\"//img1.lukou.com/static/p/emoji/emoji006.png\" data-image-name=\"[花心]\" data-emoji=\"true\" class=\"emoji\">（主要是在茵芙莎柜台做了肌肤测试，结果说我的角质有点厚，缺水，我一直以为自己角质层很薄，易过敏，就买了这款白泥清洁面膜）<br>\uD83D\uDD3A今天就心动\uD83D\uDC93的用了。还给小男友做了厕所哈哈哈<br>【价格】163元<br>【使用感受】涂上去感觉有点凉，我先做的全脸，刚开始会有刺痛感，大概一两分钟后就好了，等待了十五分钟干了根据其他红薯说的，沾湿打圈慢慢搓。我用我又敷了一张补水面膜。小男友则是敷了城野医生的收缩水。<br>【使用效果】做完没有特别紧绷感，毛孔感觉小了很多。图二毛孔肉眼可见的小也干净了许多。用的是苹果X后置摄像头。<img src=\"http://img1.lukou.com/static/p/blog/medium/0023/96/88/99/23968899.jpg\"><img src=\"http://img1.lukou.com/static/p/blog/medium/0023/96/89/00/23968900.jpg\"><img src=\"http://img1.lukou.com/static/p/blog/medium/0023/96/89/01/23968901.jpg\"><img src=\"http://img1.lukou.com/static/p/blog/medium/0023/96/89/02/23968902.jpg\"> </div>",
      "shopId": 1,
      "zuozhe": "Tolomeo"
    },
    {
      "nid": 2,
      "titele": "科颜氏白泥使用测评2",
      "add_time": "2020-03-03",
      "zhaiyao": "\uD83D\uDD3A昨日日上回来带了一大堆东西，买了好友推荐的白泥（主要是在茵芙莎柜台做了肌肤测试，结果说我的角质有点厚，缺水，我一直以为自己角质层很薄，易过敏，就买了这款白泥清洁面膜）",
      "click": 1,
      "img_url": "http://img1.lukou.com/static/p/blog/medium/0023/96/88/99/23968899.jpg",
      "content": "<div class=\"blog-content\">    \uD83D\uDD3A昨日日上回来带了一大堆东西，买了好友推荐的白泥<img src=\"//img1.lukou.com/static/p/emoji/emoji006.png\" data-image-name=\"[花心]\" data-emoji=\"true\" class=\"emoji\">（主要是在茵芙莎柜台做了肌肤测试，结果说我的角质有点厚，缺水，我一直以为自己角质层很薄，易过敏，就买了这款白泥清洁面膜）<br>\uD83D\uDD3A今天就心动\uD83D\uDC93的用了。还给小男友做了厕所哈哈哈<br>【价格】163元<br>【使用感受】涂上去感觉有点凉，我先做的全脸，刚开始会有刺痛感，大概一两分钟后就好了，等待了十五分钟干了根据其他红薯说的，沾湿打圈慢慢搓。我用我又敷了一张补水面膜。小男友则是敷了城野医生的收缩水。<br>【使用效果】做完没有特别紧绷感，毛孔感觉小了很多。图二毛孔肉眼可见的小也干净了许多。用的是苹果X后置摄像头。<img src=\"http://img1.lukou.com/static/p/blog/medium/0023/96/88/99/23968899.jpg\"><img src=\"http://img1.lukou.com/static/p/blog/medium/0023/96/89/00/23968900.jpg\"><img src=\"http://img1.lukou.com/static/p/blog/medium/0023/96/89/01/23968901.jpg\"><img src=\"http://img1.lukou.com/static/p/blog/medium/0023/96/89/02/23968902.jpg\"> </div>",
      "shopId": 1,
      "zuozhe": "Tolomeo"
    }
  ],
  "comment": [
    {
      "id": 1,
      "type": 1,
      "artid": 1,
      "user_name": "匿名用户",
      "add_time": "2020-03-03",
      "content": "我来评论一下"
    },
    {
      "id": 2,
      "type": 1,
      "artid": 1,
      "user_name": "匿名用户",
      "add_time": "2020-03-03",
      "content": "白泥出吗？"
    },
    {
      "id": 3,
      "type": 1,
      "artid": 2,
      "user_name": "2mango",
      "add_time": "2020-03-03",
      "content": "T区怎么做比较好啊……我感觉用完当时好像很干净 第二天还是脏的"
    }
  ],
  "livero": [
    {
      "id": 1,
      "sid": 1,
      "name": "禅石品质婉间风情",
      "livbor": "http://clips.vorwaerts-gmbh.de/big_buck_bunny.mp4",
      "livboeimg": "https://gw.alicdn.com/imgextra/i3/O1CN013csf7L1JMuaqTeLdM_!!0-tbCommonAudio.jpg_240x240q50s150.jpg_.webp"
    },
    {
      "id": 2,
      "sid": 2,
      "name": "禅石品质婉间风情1",
      "livbor": "http://clips.vorwaerts-gmbh.de/big_buck_bunny.mp4",
      "livboeimg": "https://img.alicdn.com/bao/uploaded/i1/248258756/O1CN01UTqHCi2EYIXWdAVEC_!!248258756-0-pixelsss.jpg_110x110q90.jpg_.webp"
    },
    {
      "id": 3,
      "sid": 4,
      "name": "禅石品质婉间风情2",
      "livbor": "http://clips.vorwaerts-gmbh.de/big_buck_bunny.mp4",
      "livboeimg": "https://gw.alicdn.com/imgextra/i3/O1CN013csf7L1JMuaqTeLdM_!!0-tbCommonAudio.jpg_240x240q50s150.jpg_.webp"
    },
    {
      "id": 4,
      "sid": 5,
      "name": "禅石品质婉间风情3",
      "livbor": "http://clips.vorwaerts-gmbh.de/big_buck_bunny.mp4",
      "livboeimg": "https://img.alicdn.com/bao/uploaded/i1/248258756/O1CN01UTqHCi2EYIXWdAVEC_!!248258756-0-pixelsss.jpg_110x110q90.jpg_.webp"
    },
    {
      "id": 5,
      "sid": 5,
      "name": "禅石品质婉间风情",
      "livbor": "http://clips.vorwaerts-gmbh.de/big_buck_bunny.mp4",
      "livboeimg": "https://img.alicdn.com/simba/img/TB11MU3blKw3KVjSZTESuwuRpXa.jpg"
    },
    {
      "id": 6,
      "sid": 7,
      "name": "禅石品质婉间风情",
      "livbor": "http://clips.vorwaerts-gmbh.de/big_buck_bunny.mp4",
      "livboeimg": "https://gw.alicdn.com/imgextra/i3/O1CN013csf7L1JMuaqTeLdM_!!0-tbCommonAudio.jpg_240x240q50s150.jpg_.webp"
    }
  ],
  "commodity": [
    {
      "id": 1,
      "fid": 1,
      "title": "华为",
      "add_time": "2019-09-09",
      "zhaiyao": "荣耀20S 李现同款 3200万人像超级夜景 4800万超广角AI三摄 麒麟810 全网通版6GB+128GB 蝶羽蓝",
      "click": 0,
      "img_url": "http://img10.360buyimg.com/n1/s160x160_jfs/t1/86253/39/14555/121706/5e65bef7E432d76ae/95e062198ddb20f0.jpg!q80.webp",
      "sell_price": 2195,
      "market_price": 2499,
      "stock_quantity": 60,
      "goods_no": "sn19992321",
      "content": "<div class=\"content_tpl\">\n<div class=\"formwork\">\n<div class=\"formwork_img\">\n<img class=\"\" src=\"http://img20.360buyimg.com/vc/jfs/t1/105511/29/13640/192518/5e5b56d8E4b79bde1/4644995228094720.jpg\" style=\"\n    width: 100%;\n\"> <img class=\"\" src=\"http://img20.360buyimg.com/vc/jfs/t1/96575/14/13479/146634/5e5b56d8E7d361475/d5e22f62c8fe62a0.jpg\" style=\"\n    width: 100%;\n\"> <img class=\"\" src=\"http://img20.360buyimg.com/vc/jfs/t1/90566/1/13648/3390417/5e5b56d8E26ebc5a0/df1b5abf8721237b.jpg\" style=\"\n    width: 100%;\n\"> \n</div>\n</div>\n</div>"
    },
      {
      "id": 2,
      "fid": 1,
      "title": "荣耀9X",
      "add_time": "2019-09-09",
      "zhaiyao": "荣耀9X 麒麟810 4000mAh续航 4800万超清夜拍 6.59英寸升降全面屏 全网通6GB+64GB 魅海蓝",
      "click": 10,
      "img_url": "https://img12.360buyimg.com/n1/s160x160_jfs/t1/86703/4/14570/167191/5e65bc4fEfd8a62a5/7a3dadd6e56874a9.jpg!q80.webp",
      "sell_price": 1299,
      "market_price": 1499,
      "stock_quantity": 60,
      "goods_no": "sn19992322"
    },
    {
      "id": 3,
      "fid": 2,
      "title": "Apple iPhone 11",
      "add_time": "2019-09-09",
      "zhaiyao": "Apple iPhone 11 (A2223) 128GB 绿色 移动联通电信4G手机 双卡双待",
      "click": 0,
      "img_url": "https://img10.360buyimg.com/n1/s160x160_jfs/t1/103460/13/14201/184977/5e6373d6Ea0ebfb9c/7bc54d2e55450dc1.jpg!q80.webp",
      "sell_price": 5999,
      "market_price": 6499,
      "stock_quantity": 60,
      "goods_no": "sn19992321"
    },
    {
      "id": 4,
      "fid": 3,
      "title": "Apple iPhone XS",
      "add_time": "2019-09-09",
      "zhaiyao": "Apple iPhone XS Max (A2104) 256GB 金色 移动联通电信4G手机 双卡双待",
      "click": 20,
      "img_url": "https://img12.360buyimg.com/n1/s160x160_jfs/t1/102163/1/14329/295629/5e6379bfEcff71637/6976358edd1bbe32.jpg!q80.webp",
      "sell_price": 7299,
      "market_price": 8499,
      "stock_quantity": 60,
      "goods_no": "sn19992332"
    }
  ],
  "classification": [
    {
      "id": 0,
      "title": "全部"
    },
    {
      "id": 1,
      "title": "日用百货"
    },
    {
      "id": 2,
      "title": "家居家装"
    },
    {
      "id": 3,
      "title": "美容个护"
    },
    {
      "id": 4,
      "title": "平价美食"
    },
    {
      "id": 5,
      "title": "母婴儿童"
    },
    {
      "id": 6,
      "title": "数码家电"
    },
    {
      "id": 7,
      "title": "服装内衣"
    },
    {
      "id": 8,
      "title": "日用百货"
    },
    {
      "id": 9,
      "title": "鞋包配饰"
    },
    {
      "id": 10,
      "title": "运动户外"
    }
  ],
  "getthumimages": [
    {
      "id": 1,
      "sid": 1,
      "img": "http://img10.360buyimg.com/n1/s160x160_jfs/t1/86253/39/14555/121706/5e65bef7E432d76ae/95e062198ddb20f0.jpg!q80.webp"
    },
    {
      "id": 2,
      "sid": 1,
      "img": "https://img12.360buyimg.com/n1/s160x160_jfs/t1/102163/1/14329/295629/5e6379bfEcff71637/6976358edd1bbe32.jpg!q80.webp"
    },

    {
      "id": 3,
      "sid": 2,
      "img": "https://img12.360buyimg.com/n1/s160x160_jfs/t1/102163/1/14329/295629/5e6379bfEcff71637/6976358edd1bbe32.jpg!q80.webp"
    }
  ],
  "shopcarlist": [
    {
      "uid": 1,
      "title": "华为",
      "cou": 1,
      "thumb_path": "http://img10.360buyimg.com/n1/s160x160_jfs/t1/86253/39/14555/121706/5e65bef7E432d76ae/95e062198ddb20f0.jpg!q80.webp",
      "sell_price": 2195

     },
    {
      "uid": 1,
      "title": "荣耀9X",
      "thumb_path": "https://img12.360buyimg.com/n1/s160x160_jfs/t1/86703/4/14570/167191/5e65bc4fEfd8a62a5/7a3dadd6e56874a9.jpg!q80.webp",
      "sell_price": 1299,
      "count": 1
    },
    {
      "uid": 1,
      "title": "Apple iPhone 11",
      "cou": 1,
      "thumb_path": "https://img10.360buyimg.com/n1/s160x160_jfs/t1/103460/13/14201/184977/5e6373d6Ea0ebfb9c/7bc54d2e55450dc1.jpg!q80.webp",
      "sell_price": 5999
    }
  ]
}
